audtorch/__init__.py
audtorch/collate.py
audtorch/samplers.py
audtorch/utils.py
audtorch/datasets/__init__.py
audtorch/datasets/audio_set.py
audtorch/datasets/base.py
audtorch/datasets/emodb.py
audtorch/datasets/libri_speech.py
audtorch/datasets/mixture.py
audtorch/datasets/mozilla_common_voice.py
audtorch/datasets/speech_commands.py
audtorch/datasets/utils.py
audtorch/datasets/voxceleb1.py
audtorch/datasets/white_noise.py
audtorch/metrics/__init__.py
audtorch/metrics/functional.py
audtorch/metrics/losses.py
audtorch/metrics/metrics.py
audtorch/transforms/__init__.py
audtorch/transforms/functional.py
audtorch/transforms/transforms.py
audtorch-0.6.4.dist-info/LICENSE
audtorch-0.6.4.dist-info/METADATA
audtorch-0.6.4.dist-info/WHEEL
audtorch-0.6.4.dist-info/top_level.txt
audtorch-0.6.4.dist-info/RECORD
