Metadata-Version: 2.1
Name: audtorch
Version: 0.6.4
Summary: Deep learning with PyTorch and audio
Home-page: https://github.com/audeering/audtorch
Author: Andreas Triantafyllopoulos, Stephan Huber, Johannes Wagner, Hagen Wierstorf
Author-email: atriant@audeering.com
License: MIT License
Project-URL: Documentation, https://audeering.github.io/audtorch/
Project-URL: Tracker, https://github.com/audeering/audtorch/issues/
Keywords: audio,torch
Platform: any
Classifier: Development Status :: 5 - Production/Stable
Classifier: Intended Audience :: Developers
Classifier: Intended Audience :: Science/Research
Classifier: License :: OSI Approved :: MIT License
Classifier: Operating System :: OS Independent
Classifier: Programming Language :: Python
Classifier: Programming Language :: Python :: 3
Classifier: Programming Language :: Python :: 3.6
Classifier: Programming Language :: Python :: 3.7
Classifier: Programming Language :: Python :: 3.8
Classifier: Topic :: Multimedia :: Sound/Audio
Requires-Dist: numpy
Requires-Dist: audiofile
Requires-Dist: librosa (>=0.8.0)
Requires-Dist: resampy
Requires-Dist: torch
Requires-Dist: pandas
Requires-Dist: tqdm
Requires-Dist: tabulate
